anymethod/__init__.py
anymethod/method.py
anymethod/method.pyi
anymethod/py.typed
anymethod-0.1.2.dist-info/METADATA
anymethod-0.1.2.dist-info/WHEEL
anymethod-0.1.2.dist-info/licenses/LICENSE
anymethod-0.1.2.dist-info/RECORD
