Metadata-Version: 2.4
Name: anymethod
Version: 0.1.2
Summary: @anymethod = instance method and @classmethod
Project-URL: Homepage, https://github.com/makukha/anymethod
Project-URL: Repository, https://github.com/makukha/anymethod
Project-URL: Issues, https://github.com/makukha/anymethod/issues
Project-URL: Changelog, https://github.com/makukha/anymethod/blob/main/CHANGELOG.md
Author-email: Michael Makukha <m.makukha@gmail.com>
License: MIT
License-File: LICENSE
Keywords: classmethod,descriptor,instance-method,polymorphism
Classifier: Development Status :: 4 - Beta
Classifier: Intended Audience :: Developers
Classifier: Intended Audience :: Information Technology
Classifier: Intended Audience :: Manufacturing
Classifier: License :: OSI Approved :: MIT License
Classifier: Operating System :: OS Independent
Classifier: Programming Language :: Python
Classifier: Programming Language :: Python :: 2
Classifier: Programming Language :: Python :: 2.7
Classifier: Programming Language :: Python :: 3
Classifier: Programming Language :: Python :: 3.5
Classifier: Programming Language :: Python :: 3.6
Classifier: Programming Language :: Python :: 3.7
Classifier: Programming Language :: Python :: 3.8
Classifier: Programming Language :: Python :: 3.9
Classifier: Programming Language :: Python :: 3.10
Classifier: Programming Language :: Python :: 3.11
Classifier: Programming Language :: Python :: 3.12
Classifier: Programming Language :: Python :: 3.13
Classifier: Programming Language :: Python :: 3.14
Classifier: Programming Language :: Python :: Implementation :: CPython
Classifier: Topic :: Software Development
Classifier: Topic :: Software Development :: Libraries
Classifier: Typing :: Typed
Requires-Python: !=3.0,!=3.1,!=3.2,!=3.3,!=3.4,>=2.7
